sklearn_ts/__init__.py
sklearn_ts/hierarchy.py
sklearn_ts/plotter.py
sklearn_ts/splitter.py
sklearn_ts/validator.py
sklearn_ts/datasets/__init__.py
sklearn_ts/datasets/covid.py
sklearn_ts/datasets/sarimax_generator.py
sklearn_ts/features/__init__.py
sklearn_ts/features/explainer.py
sklearn_ts/features/seasonality.py
sklearn_ts/models/__init__.py
sklearn_ts/models/base.py
sklearn_ts/models/exp_smoothing.py
sklearn_ts/models/naive.py
sklearn_ts/models/neural_networks.py
sklearn_ts/models/prophet.py
sklearn_ts/models/sarima.py
sklearn_ts/models/trees.py
sklearn_ts/research/__init__.py
sklearn_ts/research/simulation.py
tests/__init__.py
tests/features_test.py
tests/fourier_test.py
tests/generator_test.py
tests/mape_test.py
tests/test_suite.py
tests/validator_test.py
sklearn_ts-0.0.6.dist-info/LICENSE
sklearn_ts-0.0.6.dist-info/METADATA
sklearn_ts-0.0.6.dist-info/WHEEL
sklearn_ts-0.0.6.dist-info/top_level.txt
sklearn_ts-0.0.6.dist-info/RECORD
