Metadata-Version: 2.1
Name: sklearn-ts
Version: 0.0.6
Summary: Package for time series forecasting
Home-page: https://github.com/lady-pandas/sklearn-ts
Author: Marta Markiewicz
Author-email: m.markiewicz.pl@gmail.com
License: MIT
Keywords: time series forecasting deep learning machine learning regression ARIMA ETS
Platform: UNKNOWN
